{
  "status": "implemented",
  "agent_type": "general-implementation-agent",
  "delegation_path": ["orchestrator", "implement", "general-implementation-agent"],
  "session_id": "sess_1749507600_orchestrate",
  "task_number": 55,
  "started_at": "2026-06-09T00:00:00Z",
  "completed_at": "2026-06-09T00:30:00Z",
  "phases_completed": 4,
  "phases_total": 4,
  "completion_data": {
    "completion_summary": "Updated ROADMAP.md with 3 new Completed table rows, fixed 2 missing mermaid diagram edges (FC-->TS, FT-->TM), expanded project structure tree with Chronicle/ and Embedding/ contents, and corrected TODO.md status markers for tasks 38, 39, 41 from [COMPLETED] to [NOT STARTED]."
  },
  "artifacts": [
    {
      "type": "summary",
      "path": "specs/055_update_roadmap_completions_and_diagram/summaries/01_roadmap-update-summary.md",
      "summary": "Implementation summary for all 4 phases of ROADMAP.md update"
    }
  ],
  "memory_candidates": []
}
