{"status":"implemented","summary":"D45 soundness (8 axiom cases over serial+transitive+Euclidean frames) and completeness (canonical model with truth_lemma_d, canonical_serial, canonical_trans, canonical_eucl_from_5) proven. Full lake build passes, lean_verify clean, zero sorries.","artifacts":[{"path":"specs/109_modal_d45_soundness_completeness/summaries/01_d45-logic-summary.md","type":"summary","summary":"Implementation summary for D45 soundness and completeness"}],"blockers":[],"continuation_context":null,"next_action_hint":"complete","phases_completed":2,"phases_total":2}
