{
  "session_id": "sess_1780970224_ba1435",
  "task_numbers": [
    3,
    21,
    22
  ],
  "waves": [
    [
      3,
      21,
      22
    ]
  ],
  "dependency_graph": {
    "3": [],
    "21": [],
    "22": []
  },
  "cycle_count": 3,
  "max_cycles": 15,
  "failed_tasks": [],
  "completed_tasks": [
    3,
    21,
    22
  ],
  "current_statuses": {
    "3": "completed",
    "21": "completed",
    "22": "completed"
  },
  "task_types": {
    "3": "lean4",
    "21": "lean4",
    "22": "lean4"
  },
  "research_agents": {
    "3": "lean-research-agent",
    "21": "lean-research-agent",
    "22": "lean-research-agent"
  },
  "implement_agents": {
    "3": "lean-implementation-agent",
    "21": "lean-implementation-agent",
    "22": "lean-implementation-agent"
  }
}
